glowyr.py
glowyr-0.2.1.dist-info/LICENSE
glowyr-0.2.1.dist-info/METADATA
glowyr-0.2.1.dist-info/WHEEL
glowyr-0.2.1.dist-info/top_level.txt
glowyr-0.2.1.dist-info/RECORD
