Metadata-Version: 2.1
Name: glowyr
Version: 0.2.1
Summary: glowyr
Home-page: https://github.com/glowyr/pytools
License: MIT
Keywords: datathon
License-File: LICENSE
Requires-Dist: pandas >=0.22.0
Requires-Dist: numpy >=1.12.1
Requires-Dist: scikit-learn >=0.19.0
Requires-Dist: pydotplus >=2.0.0
Requires-Dist: matplotlib >=2.0.0
Requires-Dist: tableone >=0.8.0
